impd/__main__.py
impd/client.py
impd/cover.py
impd/icons.py
impd/impd.py
impd/threads.py
impd/timing.py
impd/ui.py
impd-0.2.3.dist-info/METADATA
impd-0.2.3.dist-info/RECORD
impd-0.2.3.dist-info/WHEEL
impd-0.2.3.dist-info/entry_points.txt
impd-0.2.3.dist-info/top_level.txt
